barbell-0.2.1.data/scripts/barbell
barbell_creator/__init__.py
barbell_creator/data/__init__.bpy
barbell_creator/data/env_file.bpy
barbell_creator/data/envs_init.bpy
barbell_creator/data/register.bpy
barbell_creator/data/setup.bpy
creator/__init__.py
barbell-0.2.1.dist-info/LICENSE
barbell-0.2.1.dist-info/METADATA
barbell-0.2.1.dist-info/WHEEL
barbell-0.2.1.dist-info/top_level.txt
barbell-0.2.1.dist-info/RECORD
